Metadata-Version: 2.1
Name: odoo8-addon-l10n-ch-lsv-dd
Version: 8.0.1.0.0.99.dev58
Summary: Create LSV and Direct Debit (postfinance) files
Home-page: http://www.compassion.ch
Author: Compassion,Odoo Community Association (OCA)
Author-email: support@odoo-community.org
License: AGPL-3
Platform: UNKNOWN
Classifier: Programming Language :: Python
Classifier: Framework :: Odoo
Classifier: License :: OSI Approved :: GNU Affero General Public License v3
Requires-Python: ~=2.7
Requires-Dist: odoo8-addon-account-banking-mandate
Requires-Dist: odoo8-addon-account-direct-debit
Requires-Dist: odoo8-addon-l10n-ch-payment-slip-base-transaction-id
Requires-Dist: odoo (<9.0a,>=8.0a)
